src/__init__.py
src/plugin.py
mkdocs_em_img2fig_plugin-0.3.3.dist-info/LICENSE
mkdocs_em_img2fig_plugin-0.3.3.dist-info/METADATA
mkdocs_em_img2fig_plugin-0.3.3.dist-info/WHEEL
mkdocs_em_img2fig_plugin-0.3.3.dist-info/entry_points.txt
mkdocs_em_img2fig_plugin-0.3.3.dist-info/top_level.txt
mkdocs_em_img2fig_plugin-0.3.3.dist-info/RECORD
