Metadata-Version: 2.1
Name: mkdocs-em-img2fig-plugin
Version: 0.3.3
Summary: A MkDocs plugin that converts markdown encoded images surrounded by two asterisks or two underscores into <figure> elements.
Home-page: https://github.com/arterm-sedov/mkdocs-em-img2fig-plugin
Author: Arterm Sedov
License: MIT
Keywords: mkdocs python markdown
Requires-Python: >=3.9
License-File: LICENSE
Requires-Dist: mkdocs
